setup.cfg
setup.py
mimicry/__init__.py
mimicry/mimic.py
mimicry.egg-info/PKG-INFO
mimicry.egg-info/SOURCES.txt
mimicry.egg-info/dependency_links.txt
mimicry.egg-info/requires.txt
mimicry.egg-info/top_level.txt