Metadata-Version: 1.0
Name: mimicry
Version: 0.3.0
Summary: MIMIC Randomized Optimization Algorithm in Python
Home-page: UNKNOWN
Author: M. Simpson, J. McGehee
Author-email: mjs2600@gmail.com, jlmcgehee21@gmail.com
License: MIT
Platform: UNKNOWN
